pyExecConnector.py
vantiqpythonexecconnector-1.3.3.dist-info/licenses/LICENSE.txt
vantiqpythonexecconnector-1.3.3.dist-info/METADATA
vantiqpythonexecconnector-1.3.3.dist-info/WHEEL
vantiqpythonexecconnector-1.3.3.dist-info/entry_points.txt
vantiqpythonexecconnector-1.3.3.dist-info/top_level.txt
vantiqpythonexecconnector-1.3.3.dist-info/RECORD
