Metadata-Version: 2.4
Name: vantiqPythonExecConnector
Version: 1.3.3
Summary: Vantiq Connector for Execution of Python Code
Home-page: https://github.com/Vantiq/vantiq-extension-sources'
Author: Vantiq, Inc
Author-email: fcarter@vantiq.com
License: MIT
Classifier: License :: OSI Approved :: MIT License
Classifier: Programming Language :: Python :: 3.10
Classifier: Programming Language :: Python :: 3.11
Classifier: Programming Language :: Python :: 3.12
Requires-Python: >=3.10
License-File: LICENSE.txt
Requires-Dist: aiohttp>=3.8
Requires-Dist: websockets>=10.2
Requires-Dist: codetiming>=1.3.0
Requires-Dist: vantiqsdk>=1.4.5
Requires-Dist: vantiqconnectorsdk>=1.3.6
Dynamic: license-file
